musicalrobot/DES.py
musicalrobot/__init__.py
musicalrobot/bulk.py
musicalrobot/data_encoding.py
musicalrobot/edge_detection.py
musicalrobot/irtemp.py
musicalrobot/pixel_analysis.py
musicalrobot/post_data.py
musicalrobot/data/10_17_19_PPA_Shallow_plate.tiff
musicalrobot/data/8_15_19_Dodecanoic_acid.tiff
musicalrobot/data/Proline_MA_5_31_19_Flat_Plate_2.jpeg
musicalrobot/data/Proline_MA_DES_5_31_19_flat_plate_1.jpeg
musicalrobot/data/wellplate.png
musicalrobot/data/inf_images/inf_1.png
musicalrobot/data/inf_images/inf_2.png
musicalrobot/data/inf_images/inf_3.png
musicalrobot/data/inf_images/inf_4.png
musicalrobot/data/inf_images/inf_5.png
musicalrobot/data/inf_images/inf_6.png
musicalrobot/data/inf_images/inf_7.png
musicalrobot/data/inf_images/inf_8.png
musicalrobot/data/inf_images/inf_9.png
musicalrobot/data/noise_images/noise_1.png
musicalrobot/data/noise_images/noise_2.png
musicalrobot/data/noise_images/noise_3.png
musicalrobot/data/noise_images/noise_4.png
musicalrobot/data/noise_images/noise_5.png
musicalrobot/data/noise_images/noise_6.png
musicalrobot/data/noise_images/noise_7.png
musicalrobot/data/noise_images/noise_8.png
musicalrobot/data/noise_images/noise_9.png
musicalrobot/models/best_derinf3.hdf5
musicalrobot/models/best_noisenet5.hdf5
musicalrobot/models/inflection_net_der3.json
musicalrobot/models/inflection_net_labels.pkl
musicalrobot/models/noise_net_bw5.json
musicalrobot/models/noise_net_labels.pkl
musicalrobot-0.993.dist-info/LICENSE
musicalrobot-0.993.dist-info/METADATA
musicalrobot-0.993.dist-info/WHEEL
musicalrobot-0.993.dist-info/top_level.txt
musicalrobot-0.993.dist-info/RECORD
