Metadata-Version: 2.1
Name: musicalrobot
Version: 0.993
Summary: A package for high-throughput measurement of deep eutectic solvents’ melting point using IR bolometry
Home-page: https://github.com/pozzocapstone/musical-robot
Author: Shrilakshmi Bonageri, Jaime Rodriguez, Sage Scheiwiller
License: MIT
Platform: UNKNOWN
Requires-Dist: numpy
Requires-Dist: pandas
Requires-Dist: scikit-image
Requires-Dist: scikit-learn
Requires-Dist: scipy
Requires-Dist: matplotlib
Requires-Dist: h5py
Requires-Dist: Keras
Requires-Dist: tensorflow
Requires-Dist: tensorflow-estimator
Requires-Dist: Keras-Applications
Requires-Dist: Keras-Preprocessing
